knight_v8/__init__.py
knight_v8/libv8py.so
knight_v8-1.1.1.dist-info/LICENSE
knight_v8-1.1.1.dist-info/METADATA
knight_v8-1.1.1.dist-info/WHEEL
knight_v8-1.1.1.dist-info/top_level.txt
knight_v8-1.1.1.dist-info/RECORD
