Metadata-Version: 2.1
Name: knight-v8
Version: 1.1.1
Summary: Minimal, modern embedded V8 for Python
Home-page: https://github.com/Esbiya/knight_v8
Author: esbiya
Author-email: 2995438815@qq.com
License: MIT
Keywords: v8
Platform: all
Classifier: Development Status :: 5 - Production/Stable
Classifier: Intended Audience :: Developers
Classifier: License :: OSI Approved :: ISC License (ISCL)
Classifier: Natural Language :: English
Classifier: Programming Language :: Python :: 2
Classifier: Programming Language :: Python :: 2.7
Classifier: Programming Language :: Python :: 3
